grandtourer/__init__.py
grandtourer/cli.py
grandtourer-0.1.7.dist-info/LICENSE
grandtourer-0.1.7.dist-info/METADATA
grandtourer-0.1.7.dist-info/WHEEL
grandtourer-0.1.7.dist-info/entry_points.txt
grandtourer-0.1.7.dist-info/RECORD
