Metadata-Version: 2.1
Name: GrandTourer
Version: 0.1.7
Summary: GrandTourer is a CLI tool for easily launching GUI applications on MacOS with a two letter command: gt
Home-page: https://github.com/WillDenby/GrandTourer
License: MIT
Author: WillDenby
Author-email: 119456795+WillDenby@users.noreply.github.com
Requires-Python: >=3.9,<4.0
Classifier: License :: OSI Approved :: MIT License
Classifier: Programming Language :: Python :: 3
Classifier: Programming Language :: Python :: 3.9
Classifier: Programming Language :: Python :: 3.10
Classifier: Programming Language :: Python :: 3.11
Classifier: Programming Language :: Python :: 3.12
Requires-Dist: click (>=8.1.7,<9.0.0)
Project-URL: Repository, https://github.com/WillDenby/GrandTourer
